LICENSE
LICENSE.txt
README.rst
setup.cfg
setup.py
peterjuice/__init__.py
peterjuice/peter.py
peterjuice.egg-info/PKG-INFO
peterjuice.egg-info/SOURCES.txt
peterjuice.egg-info/dependency_links.txt
peterjuice.egg-info/top_level.txt